ulianovorbit/__init__.py
ulianovorbit/ulianovorbit.py
ulianovorbit-1.4.0.dist-info/LICENSE
ulianovorbit-1.4.0.dist-info/METADATA
ulianovorbit-1.4.0.dist-info/WHEEL
ulianovorbit-1.4.0.dist-info/top_level.txt
ulianovorbit-1.4.0.dist-info/RECORD
