Metadata-Version: 2.1
Name: ulianovorbit
Version: 1.4.0
Summary: Library for handling Ulianov Orbit functions
Author: Policarpo Yoshin Ulianov
Author-email: poliyu77@gmail.com
License-File: LICENSE
Requires-Dist: numpy
Requires-Dist: ulianovellipse
